magmatic/__init__.py
magmatic-0.0.0.dist-info/LICENSE
magmatic-0.0.0.dist-info/METADATA
magmatic-0.0.0.dist-info/WHEEL
magmatic-0.0.0.dist-info/top_level.txt
magmatic-0.0.0.dist-info/RECORD
