Metadata-Version: 2.1
Name: magmatic
Version: 0.0.0
Summary: A robust and asynchronous Lavalink wrapper for discord.py.
Home-page: https://github.com/jay3332/magmatic
Author: jay3332 & Cryptex
License: MIT
Project-URL: Discord, https://discord.gg/FqtZ6akWpd
Project-URL: Github, https://github.com/jay3332/magmatic
Project-URL: Issue tracker, https://github.com/jay3332/magmatic/issues
Project-URL: Documentation, https://magmatic.readthedocs.io/en/latest/
Platform: UNKNOWN
Classifier: Development Status :: 4 - Beta
Classifier: Intended Audience :: Developers
Classifier: License :: OSI Approved :: MIT License
Classifier: Natural Language :: English
Classifier: Programming Language :: Python :: 3.8
Classifier: Programming Language :: Python :: 3.9
Classifier: Programming Language :: Python :: 3.10
Classifier: Topic :: Internet
Classifier: Topic :: Multimedia :: Sound/Audio
Classifier: Topic :: Software Development :: Libraries
Classifier: Topic :: Software Development :: Libraries :: Python Modules
Classifier: Topic :: Utilities
Classifier: Typing :: Typed
Requires-Python: >=3.8
License-File: LICENSE
Requires-Dist: aiohttp (<4,>=3.6.0)
